README.md
config.yaml.example
setup.py
energy_usage/__init__.py
energy_usage/config_default.yaml
energy_usage/influx_client.py
energy_usage/main.py
energy_usage/mqtt_client.py
energy_usage/sep.py
energy_usage.egg-info/PKG-INFO
energy_usage.egg-info/SOURCES.txt
energy_usage.egg-info/dependency_links.txt
energy_usage.egg-info/entry_points.txt
energy_usage.egg-info/not-zip-safe
energy_usage.egg-info/requires.txt
energy_usage.egg-info/top_level.txt