Metadata-Version: 1.0
Name: energy-usage
Version: 0.6
Summary: Records realtime energy usage from a Glowmarkt MQTT feed into influxdb
Home-page: https://gitlab.sihnon.net/ben/energy-usage
Author: Ben Roberts
Author-email: me@benroberts.net
License: UNKNOWN
Platform: UNKNOWN
